[
    {
        "status": "Active",
        "team": "NE",
        "player": "D. Maye",
        "positions": [
            "QWRT",
            "QB"
        ],
        "points": 18.25
    },
    {
        "status": "Active",
        "team": "MIA",
        "player": "D. Achane",
        "positions": [
            "RB",
            "QWRT",
            "RWT"
        ],
        "points": 19.0
    },
    {
        "status": "Active",
        "team": "BUF",
        "player": "J. Cook",
        "positions": [
            "RB",
            "QWRT",
            "RWT"
        ],
        "points": 18.9
    },
    {
        "status": "Active",
        "team": "TEN",
        "player": "C. Dike",
        "positions": [
            "RWT",
            "QWRT",
            "WR"
        ],
        "points": 0.4
    },
    {
        "status": "Active",
        "team": "TB",
        "player": "E. Egbuka",
        "positions": [
            "RWT",
            "QWRT",
            "WR"
        ],
        "points": 6.5
    },
    {
        "status": "Active",
        "team": "LAR",
        "player": "P. Nacua",
        "positions": [
            "RWT",
            "QWRT",
            "WR"
        ],
        "points": 10.8
    },
    {
        "status": "Active",
        "team": "LAR",
        "player": "T. Higbee",
        "positions": [
            "RWT",
            "TE",
            "QWRT"
        ],
        "points": 2.8
    },
    {
        "status": "Active",
        "team": "HOU",
        "player": "D. Schultz",
        "positions": [
            "RWT",
            "TE",
            "QWRT"
        ],
        "points": 8.1
    },
    {
        "status": "Active",
        "team": "CHI",
        "player": "D. Swift",
        "positions": [
            "RB",
            "QWRT",
            "RWT"
        ],
        "points": 9.0
    },
    {
        "status": "Active",
        "team": "PIT",
        "player": "J. Warren",
        "positions": [
            "RB",
            "QWRT",
            "RWT"
        ],
        "points": 7.7
    },
    {
        "status": "Active",
        "team": "SEA",
        "player": "S. Darnold",
        "positions": [
            "QWRT",
            "QB"
        ],
        "points": 8.05
    },
    {
        "status": "Bench",
        "team": "NYG",
        "player": "J. Dart",
        "positions": [
            "QWRT",
            "QB"
        ],
        "points": 0.0
    },
    {
        "status": "Bench",
        "team": "TEN",
        "player": "C. Ward",
        "positions": [
            "QWRT",
            "QB"
        ],
        "points": 15.0
    },
    {
        "status": "Bench",
        "team": "WAS",
        "player": "J. Croskey-Merritt",
        "positions": [
            "RB",
            "QWRT",
            "RWT"
        ],
        "points": 3.8
    },
    {
        "status": "Bench",
        "team": "SF",
        "player": "J. James",
        "positions": [
            "RB",
            "QWRT",
            "RWT"
        ],
        "points": 0.0
    },
    {
        "status": "Bench",
        "team": "TEN",
        "player": "T. Spears",
        "positions": [
            "RB",
            "QWRT",
            "RWT"
        ],
        "points": 5.9
    },
    {
        "status": "Bench",
        "team": "PIT",
        "player": "C. Austin III",
        "positions": [
            "RWT",
            "QWRT",
            "WR"
        ],
        "points": 1.75
    },
    {
        "status": "Bench",
        "team": "CHI",
        "player": "L. Burden",
        "positions": [
            "RWT",
            "QWRT",
            "WR"
        ],
        "points": 4.2
    },
    {
        "status": "Bench",
        "team": "DEN",
        "player": "T. Franklin",
        "positions": [
            "RWT",
            "QWRT",
            "WR"
        ],
        "points": 10.4
    },
    {
        "status": "Bench",
        "team": "HOU",
        "player": "J. Higgins",
        "positions": [
            "RWT",
            "QWRT",
            "WR"
        ],
        "points": 7.5
    },
    {
        "status": "Bench",
        "team": "LAC",
        "player": "Q. Johnston",
        "positions": [
            "RWT",
            "QWRT",
            "WR"
        ],
        "points": 0.0
    },
    {
        "status": "Bench",
        "team": "CAR",
        "player": "X. Legette",
        "positions": [
            "RWT",
            "QWRT",
            "WR"
        ],
        "points": 16.3
    },
    {
        "status": "Bench",
        "team": "NYG",
        "player": "W. Robinson",
        "positions": [
            "RWT",
            "QWRT",
            "WR"
        ],
        "points": 5.6
    },
    {
        "status": "Bench",
        "team": "SEA",
        "player": "R. Shaheed",
        "positions": [
            "RWT",
            "QWRT",
            "WR"
        ],
        "points": 4.9
    },
    {
        "status": "Bench",
        "team": "NYG",
        "player": "D. Slayton",
        "positions": [
            "RWT",
            "QWRT",
            "WR"
        ],
        "points": 0.0
    },
    {
        "status": "Bench",
        "team": "LV",
        "player": "D. Thornton",
        "positions": [
            "RWT",
            "QWRT",
            "WR"
        ],
        "points": 0.0
    },
    {
        "status": "Bench",
        "team": "GB",
        "player": "D. Wicks",
        "positions": [
            "RWT",
            "QWRT",
            "WR"
        ],
        "points": 1.4
    },
    {
        "status": "Bench",
        "team": "CAR",
        "player": "M. Evans",
        "positions": [
            "RWT",
            "TE",
            "QWRT"
        ],
        "points": 3.8
    },
    {
        "status": "Bench",
        "team": "BAL",
        "player": "I. Likely",
        "positions": [
            "RWT",
            "TE",
            "QWRT"
        ],
        "points": 2.5
    },
    {
        "status": "Active",
        "team": "ARI",
        "player": "J. Sweat",
        "positions": [
            "DL",
            "LB",
            "ID",
            "DE"
        ],
        "points": 9.0
    },
    {
        "status": "Active",
        "team": "PHI",
        "player": "J. Davis",
        "positions": [
            "DL",
            "DT",
            "ID"
        ],
        "points": 10.0
    },
    {
        "status": "Active",
        "team": "DEN",
        "player": "J. Cooper",
        "positions": [
            "DL",
            "LB",
            "ID",
            "DE"
        ],
        "points": 4.0
    },
    {
        "status": "Active",
        "team": "CIN",
        "player": "B. Carter",
        "positions": [
            "LB",
            "ID"
        ],
        "points": 4.0
    },
    {
        "status": "Active",
        "team": "TB",
        "player": "S. Dennis",
        "positions": [
            "LB",
            "ID"
        ],
        "points": 13.0
    },
    {
        "status": "Active",
        "team": "SEA",
        "player": "T. Knight",
        "positions": [
            "LB",
            "ID"
        ],
        "points": 1.0
    },
    {
        "status": "Active",
        "team": "MIN",
        "player": "I. Rodgers",
        "positions": [
            "DB",
            "CB",
            "ID"
        ],
        "points": 7.0
    },
    {
        "status": "Active",
        "team": "TB",
        "player": "T. Smith",
        "positions": [
            "DB",
            "CB",
            "ID",
            "S"
        ],
        "points": 11.0
    },
    {
        "status": "Active",
        "team": "CIN",
        "player": "J. Battle",
        "positions": [
            "DB",
            "CB",
            "ID",
            "S"
        ],
        "points": 9.0
    },
    {
        "status": "Active",
        "team": "CAR",
        "player": "T. Moehrig",
        "positions": [
            "DB",
            "ID",
            "S"
        ],
        "points": 11.0
    },
    {
        "status": "Active",
        "team": "BAL",
        "player": "M. Starks",
        "positions": [
            "DB",
            "ID",
            "S"
        ],
        "points": 2.0
    },
    {
        "status": "Bench",
        "team": "WAS",
        "player": "D. Payne",
        "positions": [
            "DL",
            "DT",
            "ID"
        ],
        "points": 0.0
    },
    {
        "status": "Bench",
        "team": "PIT",
        "player": "A. Highsmith",
        "positions": [
            "DL",
            "LB",
            "ID",
            "DE"
        ],
        "points": 0.0
    },
    {
        "status": "Bench",
        "team": "DET",
        "player": "A. Muhammad",
        "positions": [
            "DL",
            "LB",
            "ID",
            "DE"
        ],
        "points": 2.0
    },
    {
        "status": "Bench",
        "team": "LAC",
        "player": "J. Oweh",
        "positions": [
            "DL",
            "LB",
            "ID",
            "DE"
        ],
        "points": 3.0
    },
    {
        "status": "Bench",
        "team": "IND",
        "player": "G. Pratt",
        "positions": [
            "LB",
            "ID"
        ],
        "points": 0.0
    },
    {
        "status": "Bench",
        "team": "PIT",
        "player": "J. Sawyer",
        "positions": [
            "DL",
            "LB",
            "ID",
            "DE"
        ],
        "points": 2.0
    },
    {
        "status": "Bench",
        "team": "MIN",
        "player": "B. Murphy",
        "positions": [
            "DB",
            "CB",
            "ID"
        ],
        "points": 8.0
    },
    {
        "status": "Bench",
        "team": "NYJ",
        "player": "T. Adams",
        "positions": [
            "DB",
            "ID",
            "S"
        ],
        "points": 6.0
    },
    {
        "status": "Bench",
        "team": "ARI",
        "player": "B. Baker",
        "positions": [
            "DB",
            "ID",
            "S"
        ],
        "points": 8.0
    },
    {
        "status": "Bench",
        "team": "MIA",
        "player": "M. Fitzpatrick",
        "positions": [
            "DB",
            "ID",
            "S"
        ],
        "points": 13.0
    },
    {
        "status": "Bench",
        "team": "NYG",
        "player": "T. Nubin",
        "positions": [
            "DB",
            "CB",
            "ID",
            "S"
        ],
        "points": 0.0
    },
    {
        "status": "Active",
        "team": "BAL",
        "player": "T. Loop",
        "positions": [
            "K"
        ],
        "points": 9.0
    }
]