[
    {
        "status": "Active",
        "team": "NYJ",
        "player": "J. Fields",
        "positions": [
            "QWRT",
            "QB"
        ],
        "points": 26.75,
        "perfect": "QB1"
    },
    {
        "status": "Active",
        "team": "HOU",
        "player": "N. Chubb",
        "positions": [
            "RWT",
            "RB",
            "QWRT"
        ],
        "points": 12.1,
        "perfect": "RB2"
    },
    {
        "status": "Active",
        "team": "IND",
        "player": "J. Taylor",
        "positions": [
            "RWT",
            "RB",
            "QWRT"
        ],
        "points": 32.1,
        "perfect": "RB1"
    },
    {
        "status": "Active",
        "team": "TB",
        "player": "C. Godwin",
        "positions": [
            "QWRT",
            "RWT",
            "WR"
        ],
        "points": 4.1,
        "perfect": null
    },
    {
        "status": "Active",
        "team": "DAL",
        "player": "G. Pickens",
        "positions": [
            "QWRT",
            "RWT",
            "WR"
        ],
        "points": 12.7,
        "perfect": "WR1"
    },
    {
        "status": "Active",
        "team": "BUF",
        "player": "K. Shakir",
        "positions": [
            "QWRT",
            "RWT",
            "WR"
        ],
        "points": 9.0,
        "perfect": "WR3"
    },
    {
        "status": "Active",
        "team": "WAS",
        "player": "Z. Ertz",
        "positions": [
            "QWRT",
            "RWT",
            "TE"
        ],
        "points": 0.0,
        "perfect": null
    },
    {
        "status": "Active",
        "team": "CAR",
        "player": "T. Tremble",
        "positions": [
            "QWRT",
            "RWT",
            "TE"
        ],
        "points": 2.2,
        "perfect": "TE1"
    },
    {
        "status": "Active",
        "team": "NYG",
        "player": "C. Skattebo",
        "positions": [
            "RWT",
            "RB",
            "QWRT"
        ],
        "points": 11.4,
        "perfect": "RWT1"
    },
    {
        "status": "Active",
        "team": "SEA",
        "player": "K. Walker III",
        "positions": [
            "RWT",
            "RB",
            "QWRT"
        ],
        "points": 9.1,
        "perfect": "RWT2"
    },
    {
        "status": "Active",
        "team": "BUF",
        "player": "J. Allen",
        "positions": [
            "QWRT",
            "QB"
        ],
        "points": 21.95,
        "perfect": "QWRT1"
    },
    {
        "status": "Bench",
        "team": "CIN",
        "player": "J. Flacco",
        "positions": [
            "QWRT",
            "QB"
        ],
        "points": 0.0,
        "perfect": null
    },
    {
        "status": "Bench",
        "team": "(N/A)",
        "player": "D. Ridder",
        "positions": [
            "QWRT",
            "QB"
        ],
        "points": 0.0,
        "perfect": null
    },
    {
        "status": "Bench",
        "team": "NYG",
        "player": "R. Wilson",
        "positions": [
            "QWRT",
            "QB"
        ],
        "points": 0.0,
        "perfect": null
    },
    {
        "status": "Bench",
        "team": "CAR",
        "player": "J. Brooks",
        "positions": [
            "RWT",
            "RB",
            "QWRT"
        ],
        "points": 0.0,
        "perfect": null
    },
    {
        "status": "Bench",
        "team": "LV",
        "player": "R. Mostert",
        "positions": [
            "RWT",
            "RB",
            "QWRT"
        ],
        "points": 3.35,
        "perfect": null
    },
    {
        "status": "Bench",
        "team": "HOU",
        "player": "D. Pierce",
        "positions": [
            "RWT",
            "RB",
            "QWRT"
        ],
        "points": 2.1,
        "perfect": null
    },
    {
        "status": "Bench",
        "team": "(N/A)",
        "player": "M. Hardman",
        "positions": [
            "QWRT",
            "RWT",
            "WR"
        ],
        "points": 0.0,
        "perfect": null
    },
    {
        "status": "Bench",
        "team": "CIN",
        "player": "T. Higgins",
        "positions": [
            "QWRT",
            "RWT",
            "WR"
        ],
        "points": 11.7,
        "perfect": "WR2"
    },
    {
        "status": "Bench",
        "team": "TEN",
        "player": "V. Jefferson",
        "positions": [
            "QWRT",
            "RWT",
            "WR"
        ],
        "points": 0.0,
        "perfect": null
    },
    {
        "status": "Bench",
        "team": "(N/A)",
        "player": "D. Johnson",
        "positions": [
            "QWRT",
            "RWT",
            "WR"
        ],
        "points": 0.0,
        "perfect": null
    },
    {
        "status": "Bench",
        "team": "DAL",
        "player": "J. Mingo",
        "positions": [
            "QWRT",
            "RWT",
            "WR"
        ],
        "points": 0.0,
        "perfect": null
    },
    {
        "status": "Bench",
        "team": "BUF",
        "player": "J. Palmer",
        "positions": [
            "QWRT",
            "RWT",
            "WR"
        ],
        "points": 4.6,
        "perfect": null
    },
    {
        "status": "Bench",
        "team": "MIN",
        "player": "A. Thielen",
        "positions": [
            "QWRT",
            "RWT",
            "WR"
        ],
        "points": 0.0,
        "perfect": null
    },
    {
        "status": "Bench",
        "team": "SF",
        "player": "L. Farrell",
        "positions": [
            "QWRT",
            "RWT",
            "TE"
        ],
        "points": 1.3,
        "perfect": "TE2"
    },
    {
        "status": "Active",
        "team": "DAL",
        "player": "K. Clark",
        "positions": [
            "DE",
            "DT",
            "ID",
            "DL"
        ],
        "points": 7.0,
        "perfect": "DT1"
    },
    {
        "status": "Active",
        "team": "LAR",
        "player": "B. Fiske",
        "positions": [
            "DE",
            "DT",
            "ID",
            "DL"
        ],
        "points": 3.0,
        "perfect": null
    },
    {
        "status": "Active",
        "team": "BUF",
        "player": "A. Epenesa",
        "positions": [
            "DE",
            "ID",
            "DL"
        ],
        "points": 8.0,
        "perfect": "DL1"
    },
    {
        "status": "Active",
        "team": "HOU",
        "player": "A. Al-Shaair",
        "positions": [
            "LB",
            "ID"
        ],
        "points": 7.0,
        "perfect": null
    },
    {
        "status": "Active",
        "team": "KC",
        "player": "N. Bolton",
        "positions": [
            "LB",
            "ID"
        ],
        "points": 20.0,
        "perfect": "LB1"
    },
    {
        "status": "Active",
        "team": "LAR",
        "player": "B. Young",
        "positions": [
            "LB",
            "ID"
        ],
        "points": 9.0,
        "perfect": null
    },
    {
        "status": "Active",
        "team": "HOU",
        "player": "K. Lassiter",
        "positions": [
            "ID",
            "DB",
            "CB",
            "S"
        ],
        "points": 13.0,
        "perfect": "CB1"
    },
    {
        "status": "Active",
        "team": "WAS",
        "player": "J. Martin",
        "positions": [
            "ID",
            "DB",
            "CB",
            "S"
        ],
        "points": 12.0,
        "perfect": "CB2"
    },
    {
        "status": "Active",
        "team": "DET",
        "player": "B. Branch",
        "positions": [
            "ID",
            "DB",
            "CB",
            "S"
        ],
        "points": 4.0,
        "perfect": null
    },
    {
        "status": "Active",
        "team": "NYG",
        "player": "J. Holland",
        "positions": [
            "ID",
            "DB",
            "S"
        ],
        "points": 5.0,
        "perfect": "S2"
    },
    {
        "status": "Active",
        "team": "JAX",
        "player": "F. Oluokun",
        "positions": [
            "LB",
            "ID"
        ],
        "points": 14.0,
        "perfect": "ID1"
    },
    {
        "status": "Bench",
        "team": "DAL",
        "player": "D. Ezeiruaku",
        "positions": [
            "DE",
            "ID",
            "DL"
        ],
        "points": 3.0,
        "perfect": null
    },
    {
        "status": "Bench",
        "team": "TEN",
        "player": "S. Joseph-Day",
        "positions": [
            "DE",
            "DT",
            "ID",
            "DL"
        ],
        "points": 15.0,
        "perfect": "DE1"
    },
    {
        "status": "Bench",
        "team": "GB",
        "player": "D. Wyatt",
        "positions": [
            "DT",
            "ID",
            "DL"
        ],
        "points": 0.0,
        "perfect": null
    },
    {
        "status": "Bench",
        "team": "MIA",
        "player": "J. Brooks",
        "positions": [
            "LB",
            "ID"
        ],
        "points": 16.0,
        "perfect": "LB2"
    },
    {
        "status": "Bench",
        "team": "ARI",
        "player": "Z. Collins",
        "positions": [
            "LB",
            "ID"
        ],
        "points": 4.0,
        "perfect": null
    },
    {
        "status": "Bench",
        "team": "IND",
        "player": "Z. Franklin",
        "positions": [
            "LB",
            "ID"
        ],
        "points": 15.0,
        "perfect": "LB3"
    },
    {
        "status": "Bench",
        "team": "(N/A)",
        "player": "J. Hicks",
        "positions": [
            "LB",
            "ID"
        ],
        "points": 0.0,
        "perfect": null
    },
    {
        "status": "Bench",
        "team": "GB",
        "player": "Q. Walker",
        "positions": [
            "LB",
            "ID"
        ],
        "points": 0.0,
        "perfect": null
    },
    {
        "status": "Bench",
        "team": "ATL",
        "player": "D. Alford",
        "positions": [
            "ID",
            "DB",
            "CB",
            "S"
        ],
        "points": 0.0,
        "perfect": null
    },
    {
        "status": "Bench",
        "team": "DET",
        "player": "T. Arnold",
        "positions": [
            "ID",
            "DB",
            "CB",
            "S"
        ],
        "points": 7.0,
        "perfect": "S1"
    },
    {
        "status": "Bench",
        "team": "TB",
        "player": "J. Dean",
        "positions": [
            "ID",
            "DB",
            "CB"
        ],
        "points": 0.0,
        "perfect": null
    },
    {
        "status": "Bench",
        "team": "ARI",
        "player": "M. Melton",
        "positions": [
            "ID",
            "DB",
            "CB",
            "S"
        ],
        "points": 0.0,
        "perfect": null
    },
    {
        "status": "Bench",
        "team": "TEN",
        "player": "L. Sneed",
        "positions": [
            "ID",
            "DB",
            "CB",
            "S"
        ],
        "points": 4.0,
        "perfect": null
    },
    {
        "status": "Bench",
        "team": "CHI",
        "player": "C. Gardner-Johnson",
        "positions": [
            "ID",
            "DB",
            "S"
        ],
        "points": 0.0,
        "perfect": null
    },
    {
        "status": "Bench",
        "team": "GB",
        "player": "X. McKinney",
        "positions": [
            "ID",
            "DB",
            "CB",
            "S"
        ],
        "points": 0.0,
        "perfect": null
    },
    {
        "status": "Active",
        "team": "LV",
        "player": "D. Carlson",
        "positions": [
            "K"
        ],
        "points": 4.0,
        "perfect": "K1"
    },
    {
        "status": "Bench",
        "team": "HOU",
        "player": "M. Wright",
        "positions": [
            "K"
        ],
        "points": 0.0,
        "perfect": null
    }
]